FPGA/AHB_LED/AHB2LED.v
module AHB2LED(

			input wire HSEL,
		//Global Signal
			input wire HCLK,
			input wire HRESETn,
		//Address, Control & Write Data
			input wire HREADY,
			input wire [31:0] HADDR,
			input wire [1:0] HTRANS,
			input wire HWRITE,
			input wire [2:0] HSIZE,
			
			input wire [31:0] HWDATA,
		// Transfer Response & Read Data
			output wire HREADYOUT,
			output wire [31:0] HRDATA,
		//LED Output
			output wire [7:0] LED
);

//Address Phase Sampling Registers
  reg rHSEL;
  reg [31:0] rHADDR;
  reg [1:0] rHTRANS;
  reg rHWRITE;
  reg [2:0] rHSIZE;

  reg [7:0] rLED;
 
//Address Phase Sampling
  always @(posedge HCLK or negedge HRESETn)
  begin
	 if(!HRESETn)
	 begin
		rHSEL		<= 1'b0;
		rHADDR	<= 32'h0;
		rHTRANS	<= 2'b00;
		rHWRITE	<= 1'b0;
		rHSIZE	<= 3'b000;
	 end
    else if(HREADY)
    begin
      rHSEL		<= HSEL;
		rHADDR	<= HADDR;
		rHTRANS	<= HTRANS;
		rHWRITE	<= HWRITE;
		rHSIZE	<= HSIZE;
    end
  end

//Data Phase data transfer
  always @(posedge HCLK or negedge HRESETn)
  begin
    if(!HRESETn)
      rLED <= 8'b0000_0000;
    else if(rHSEL & rHWRITE & rHTRANS[1])
      rLED <= HWDATA[7:0];
  end

//Transfer Response
  assign HREADYOUT = 1'b1; 

//Read Data  
  assign HRDATA = {24'h0000_00,rLED};

  assign LED = rLED;


endmodule

FPGA/AHB_LED/tb.v
`timescale 1ns/1ps

module tb;

  // Global signals
  reg HCLK;
  reg HRESETn;

  // Master side signals
  reg HSEL;
  reg HREADY;
  reg [31:0] HADDR;
  reg [1:0]  HTRANS;
  reg HWRITE;
  reg [2:0]  HSIZE;
  reg [31:0] HWDATA;

  // Slave response signals
  wire HREADYOUT;
  wire [31:0] HRDATA;

  // LED output
  wire [7:0] LED;

  // Clock generation
  initial begin
    HCLK = 0;
    forever #5 HCLK = ~HCLK; // 100 MHz clock
  end

  // Reset
  initial begin
    HRESETn = 0;
    #20 HRESETn = 1;
  end

  // Stimulus
  initial begin
    HSEL    = 1'b0;
    HREADY  = 1'b0;
    HADDR   = 32'h0;
    HTRANS  = 2'b00;
    HWRITE  = 1'b0;
    HSIZE   = 3'b000;
    HWDATA  = 32'h0;

    // Wait for reset deassertion
    @(posedge HRESETn);

    // Example transactions
    @(posedge HCLK);
    HSEL   = 1'b1;
    HREADY = 1'b1;
    HTRANS = 2'b11;
    HWRITE = 1'b1;
    HSIZE  = 3'b001;

    #10 HWDATA = 32'h000;
    #10 HWDATA = 32'h001;
    #10 HWDATA = 32'h010;
    #10 HWDATA = 32'h100;
    #10 HWDATA = 32'h101;
    #10 HWDATA = 32'h111;

    #50 $finish;
  end

  // DUT instantiation
  AHB2LED led1 (
    .HSEL(HSEL),
    .HCLK(HCLK),
    .HRESETn(HRESETn),
    .HREADY(HREADY),
    .HADDR(HADDR),
    .HTRANS(HTRANS),
    .HWRITE(HWRITE),
    .HSIZE(HSIZE),
    .HWDATA(HWDATA),
    .HREADYOUT(HREADYOUT),
    .HRDATA(HRDATA),
    .LED(LED)
  );

  // VCD dump
  initial begin
    $dumpfile("dump.vcd");
    $dumpvars(0, tb);
  end

endmodule

FPGA/AHB_LED/dump.vcd
$date
	Sat Jul 11 20:39:09 2026
$end
$version
	Icarus Verilog
$end
$timescale
	1ps
$end
$scope module tb $end
$var wire 1 ! HREADYOUT $end
$var wire 8 " LED [7:0] $end
$var wire 32 # HRDATA [31:0] $end
$var reg 32 $ HADDR [31:0] $end
$var reg 1 % HCLK $end
$var reg 1 & HREADY $end
$var reg 1 ' HRESETn $end
$var reg 1 ( HSEL $end
$var reg 3 ) HSIZE [2:0] $end
$var reg 2 * HTRANS [1:0] $end
$var reg 32 + HWDATA [31:0] $end
$var reg 1 , HWRITE $end
$scope module led1 $end
$var wire 32 - HADDR [31:0] $end
$var wire 1 % HCLK $end
$var wire 1 & HREADY $end
$var wire 1 ! HREADYOUT $end
$var wire 1 ' HRESETn $end
$var wire 1 ( HSEL $end
$var wire 3 . HSIZE [2:0] $end
$var wire 2 / HTRANS [1:0] $end
$var wire 32 0 HWDATA [31:0] $end
$var wire 1 , HWRITE $end
$var wire 8 1 LED [7:0] $end
$var wire 32 2 HRDATA [31:0] $end
$var reg 32 3 rHADDR [31:0] $end
$var reg 1 4 rHSEL $end
$var reg 3 5 rHSIZE [2:0] $end
$var reg 2 6 rHTRANS [1:0] $end
$var reg 1 7 rHWRITE $end
$var reg 8 8 rLED [7:0] $end
$upscope $end
$upscope $end
$enddefinitions $end
$comment Show the parameter values. $end
$dumpall
$end
#0
$dumpvars
b0 8
07
b0 6
b0 5
04
b0 3
b0 2
b0 1
b0 0
b0 /
b0 .
b0 -
0,
b0 +
b0 *
b0 )
0(
0'
0&
0%
b0 $
b0 #
b0 "
1!
$end
#5000
1%
#10000
0%
#15000
1%
#20000
0%
1'
#25000
b1 5
17
b11 6
14
b1 )
b1 .
1,
b11 *
b11 /
1&
1(
1%
#30000
0%
#35000
1%
#40000
0%
#45000
b1 #
b1 2
b1 "
b1 1
b1 8
1%
b1 +
b1 0
#50000
0%
#55000
b10000 #
b10000 2
b10000 "
b10000 1
b10000 8
1%
b10000 +
b10000 0
#60000
0%
#65000
b0 #
b0 2
b0 "
b0 1
b0 8
1%
b100000000 +
b100000000 0
#70000
0%
#75000
b1 #
b1 2
b1 "
b1 1
b1 8
1%
b100000001 +
b100000001 0
#80000
0%
#85000
b10001 #
b10001 2
b10001 "
b10001 1
b10001 8
1%
b100010001 +
b100010001 0
